odoo8_addon_base_vat_sanitized-8.0.1.0.0.99.dev8-py2.7-nspkg.pth
odoo8_addon_base_vat_sanitized-8.0.1.0.0.99.dev8.dist-info/METADATA
odoo8_addon_base_vat_sanitized-8.0.1.0.0.99.dev8.dist-info/RECORD
odoo8_addon_base_vat_sanitized-8.0.1.0.0.99.dev8.dist-info/WHEEL
odoo8_addon_base_vat_sanitized-8.0.1.0.0.99.dev8.dist-info/namespace_packages.txt
odoo8_addon_base_vat_sanitized-8.0.1.0.0.99.dev8.dist-info/top_level.txt
odoo_addons/base_vat_sanitized/README.rst
odoo_addons/base_vat_sanitized/__init__.py
odoo_addons/base_vat_sanitized/__openerp__.py
odoo_addons/base_vat_sanitized/i18n/base_vat_sanitized.pot
odoo_addons/base_vat_sanitized/i18n/de.po
odoo_addons/base_vat_sanitized/i18n/es.po
odoo_addons/base_vat_sanitized/i18n/eu.po
odoo_addons/base_vat_sanitized/i18n/sl.po
odoo_addons/base_vat_sanitized/models/__init__.py
odoo_addons/base_vat_sanitized/models/res_partner.py
odoo_addons/base_vat_sanitized/static/description/icon.png
odoo_addons/base_vat_sanitized/tests/__init__.py
odoo_addons/base_vat_sanitized/tests/test_vat.py
